openeew/__init__.py
openeew/data/__init__.py
openeew/data/aws.py
openeew/data/df.py
openeew/data/record.py
openeew-0.5.0.dist-info/LICENSE
openeew-0.5.0.dist-info/METADATA
openeew-0.5.0.dist-info/WHEEL
openeew-0.5.0.dist-info/top_level.txt
openeew-0.5.0.dist-info/RECORD
