Metadata-Version: 2.1
Name: openeew
Version: 0.5.0
Summary: OpenEEW library for Python
Home-page: http://github.com/grillo/openeew-python
Author: Grillo
Author-email: openeew@grillo.io
License: Apache License 2.0
Platform: UNKNOWN
Classifier: License :: OSI Approved :: Apache Software License
Classifier: Programming Language :: Python :: 3
Classifier: Programming Language :: Python :: 3.5
Classifier: Programming Language :: Python :: 3.6
Classifier: Programming Language :: Python :: 3.7
Requires-Python: >=3.5
Requires-Dist: pandas
Requires-Dist: aioboto3
